ChaolingQihaoVol1/Dockerfile
ChaolingQihaoVol1/README.md
ChaolingQihaoVol1/__init__.py
ChaolingQihaoVol1/__main__.py
ChaolingQihaoVol1/file.epub
ChaolingQihaoVol1/index.html
ChaolingQihaoVol1/css/__init__.py
ChaolingQihaoVol1/css/annotations.css
ChaolingQihaoVol1/css/main.css
ChaolingQihaoVol1/css/normalize.css
ChaolingQihaoVol1/css/popup.css
ChaolingQihaoVol1/font/__init__.py
ChaolingQihaoVol1/font/fontello.eot
ChaolingQihaoVol1/font/fontello.svg
ChaolingQihaoVol1/font/fontello.ttf
ChaolingQihaoVol1/font/fontello.woff
ChaolingQihaoVol1/img/__init__.py
ChaolingQihaoVol1/img/annotator-glyph-sprite.png
ChaolingQihaoVol1/img/annotator-icon-sprite.png
ChaolingQihaoVol1/img/apple-touch-icon.png
ChaolingQihaoVol1/img/cancelfullscreen.png
ChaolingQihaoVol1/img/close.png
ChaolingQihaoVol1/img/fullscreen.png
ChaolingQihaoVol1/img/loader.gif
ChaolingQihaoVol1/img/menu-icon.png
ChaolingQihaoVol1/img/save.png
ChaolingQihaoVol1/img/saved.png
ChaolingQihaoVol1/img/settings-s.png
ChaolingQihaoVol1/img/settings.png
ChaolingQihaoVol1/img/star.png
ChaolingQihaoVol1/js/__init__.py
ChaolingQihaoVol1/js/epub.js
ChaolingQihaoVol1/js/epub.min.js
ChaolingQihaoVol1/js/epub.min.map
ChaolingQihaoVol1/js/hooks.min.js
ChaolingQihaoVol1/js/hooks.min.map
ChaolingQihaoVol1/js/reader.js
ChaolingQihaoVol1/js/reader.js.map
ChaolingQihaoVol1/js/reader.min.js
ChaolingQihaoVol1/js/reader.min.map
ChaolingQihaoVol1/js/hooks/__init__.py
ChaolingQihaoVol1/js/hooks/extensions/__init__.py
ChaolingQihaoVol1/js/hooks/extensions/highlight.js
ChaolingQihaoVol1/js/libs/__init__.py
ChaolingQihaoVol1/js/libs/jquery.min.js
ChaolingQihaoVol1/js/libs/localforage.min.js
ChaolingQihaoVol1/js/libs/screenfull.js
ChaolingQihaoVol1/js/libs/screenfull.min.js
ChaolingQihaoVol1/js/libs/zip.min.js
ChaolingQihaoVol1/js/plugins/__init__.py
ChaolingQihaoVol1/js/plugins/hypothesis.js
ChaolingQihaoVol1/js/plugins/search.js
chaoling_qihao_vol1-2022.10.9.1.dist-info/METADATA
chaoling_qihao_vol1-2022.10.9.1.dist-info/WHEEL
chaoling_qihao_vol1-2022.10.9.1.dist-info/entry_points.txt
chaoling_qihao_vol1-2022.10.9.1.dist-info/top_level.txt
chaoling_qihao_vol1-2022.10.9.1.dist-info/RECORD
